supervisor_detect/__init__.py
supervisor_detect/base.py
supervisor_detect/datasets.py
supervisor_detect/exceptions.py
supervisor_detect/version.py
supervisor_detect/ad/__init__.py
supervisor_detect/ad/adversarialae.py
supervisor_detect/ad/model_distillation.py
supervisor_detect/cd/__init__.py
supervisor_detect/cd/_domain_clf.py
supervisor_detect/cd/base.py
supervisor_detect/cd/base_online.py
supervisor_detect/cd/chisquare.py
supervisor_detect/cd/classifier.py
supervisor_detect/cd/context_aware.py
supervisor_detect/cd/cvm.py
supervisor_detect/cd/cvm_online.py
supervisor_detect/cd/fet.py
supervisor_detect/cd/fet_online.py
supervisor_detect/cd/ks.py
supervisor_detect/cd/learned_kernel.py
supervisor_detect/cd/lsdd.py
supervisor_detect/cd/lsdd_online.py
supervisor_detect/cd/mmd.py
supervisor_detect/cd/mmd_online.py
supervisor_detect/cd/model_uncertainty.py
supervisor_detect/cd/preprocess.py
supervisor_detect/cd/spot_the_diff.py
supervisor_detect/cd/tabular.py
supervisor_detect/cd/utils.py
supervisor_detect/cd/keops/__init__.py
supervisor_detect/cd/keops/learned_kernel.py
supervisor_detect/cd/keops/mmd.py
supervisor_detect/cd/pytorch/__init__.py
supervisor_detect/cd/pytorch/classifier.py
supervisor_detect/cd/pytorch/context_aware.py
supervisor_detect/cd/pytorch/learned_kernel.py
supervisor_detect/cd/pytorch/lsdd.py
supervisor_detect/cd/pytorch/lsdd_online.py
supervisor_detect/cd/pytorch/mmd.py
supervisor_detect/cd/pytorch/mmd_online.py
supervisor_detect/cd/pytorch/preprocess.py
supervisor_detect/cd/pytorch/spot_the_diff.py
supervisor_detect/cd/pytorch/utils.py
supervisor_detect/cd/sklearn/__init__.py
supervisor_detect/cd/sklearn/classifier.py
supervisor_detect/cd/tensorflow/__init__.py
supervisor_detect/cd/tensorflow/classifier.py
supervisor_detect/cd/tensorflow/context_aware.py
supervisor_detect/cd/tensorflow/learned_kernel.py
supervisor_detect/cd/tensorflow/lsdd.py
supervisor_detect/cd/tensorflow/lsdd_online.py
supervisor_detect/cd/tensorflow/mmd.py
kozmo_supervisor_detect-0.12.1.dev0.dist-info/LICENSE
kozmo_supervisor_detect-0.12.1.dev0.dist-info/METADATA
kozmo_supervisor_detect-0.12.1.dev0.dist-info/WHEEL
kozmo_supervisor_detect-0.12.1.dev0.dist-info/entry_points.txt
kozmo_supervisor_detect-0.12.1.dev0.dist-info/top_level.txt
kozmo_supervisor_detect-0.12.1.dev0.dist-info/RECORD
