Metadata-Version: 2.1
Name: kozmo-supervisor-detect
Version: 0.12.1.dev0
Summary: Algorithms for outlier detection, concept drift and metrics.
Home-page: https://github.com/kozmoai/supervisor-detect
Author: KozmoAI Ltd.
Author-email: hello@kozmoai.io
License: Business Source License 1.1
Classifier: Intended Audience :: Science/Research
Classifier: Operating System :: OS Independent
Classifier: Programming Language :: Python :: 3
Classifier: Programming Language :: Python :: 3.8
Classifier: Programming Language :: Python :: 3.9
Classifier: Programming Language :: Python :: 3.10
Classifier: Programming Language :: Python :: 3.11
Classifier: License :: Other/Proprietary License
Classifier: Topic :: Scientific/Engineering
Requires-Python: >=3.8
License-File: LICENSE
Requires-Dist: matplotlib <4.0.0,>=3.0.0
Requires-Dist: numpy <2.0.0,>=1.16.2
Requires-Dist: pandas <3.0.0,>=1.0.0
Requires-Dist: Pillow <11.0.0,>=5.4.1
Requires-Dist: opencv-python <5.0.0,>=3.2.0
Requires-Dist: scipy <2.0.0,>=1.3.0
Requires-Dist: scikit-image <0.23,>=0.19
Requires-Dist: scikit-learn <2.0.0,>=0.20.2
Requires-Dist: transformers <5.0.0,>=4.0.0
Requires-Dist: dill <0.4.0,>=0.3.0
Requires-Dist: tqdm <5.0.0,>=4.28.1
Requires-Dist: requests <3.0.0,>=2.21.0
Requires-Dist: pydantic <3.0.0,>=1.8.0
Requires-Dist: toml <1.0.0,>=0.10.1
Requires-Dist: catalogue <3.0.0,>=2.0.0
Requires-Dist: numba !=0.54.0,<0.60.0,>=0.50.0
Requires-Dist: typing-extensions >=3.7.4.3
Provides-Extra: all
Requires-Dist: prophet <2.0.0,>=1.1.0 ; extra == 'all'
Requires-Dist: tensorflow-probability <0.23.0,>=0.8.0 ; extra == 'all'
Requires-Dist: tensorflow !=2.6.0,!=2.6.1,<2.15.0,>=2.2.0 ; extra == 'all'
Requires-Dist: pykeops <2.3.0,>=2.0.0 ; extra == 'all'
Requires-Dist: torch <3.0.0,>=1.7.0 ; extra == 'all'
Provides-Extra: keops
Requires-Dist: pykeops <2.3.0,>=2.0.0 ; extra == 'keops'
Requires-Dist: torch <3.0.0,>=1.7.0 ; extra == 'keops'
Provides-Extra: prophet
Requires-Dist: prophet <2.0.0,>=1.1.0 ; extra == 'prophet'
Provides-Extra: tensorflow
Requires-Dist: tensorflow-probability <0.23.0,>=0.8.0 ; extra == 'tensorflow'
Requires-Dist: tensorflow !=2.6.0,!=2.6.1,<2.15.0,>=2.2.0 ; extra == 'tensorflow'
Provides-Extra: torch
Requires-Dist: torch <3.0.0,>=1.7.0 ; extra == 'torch'
